vicky/__init__.py
vicky/clients.py
vicky/deployment.py
vicky/exceptions.py
vicky/utils.py
vicky/scripts/__init__.py
vicky/scripts/vicky.py
vicky-0.3.4.dist-info/METADATA
vicky-0.3.4.dist-info/WHEEL
vicky-0.3.4.dist-info/entry_points.txt
vicky-0.3.4.dist-info/top_level.txt
vicky-0.3.4.dist-info/RECORD
