Metadata-Version: 2.1
Name: vicky
Version: 0.3.4
Requires-Dist: boto3
Requires-Dist: click
Requires-Dist: requests
